{
  "project_info": {
    "project_number": "673118911922",
    "project_id": "chat-app-fc2b5",
    "storage_bucket": "chat-app-fc2b5.firebasestorage.app"
  },
  "client": [
    {
      "client_info": {
        "mobilesdk_app_id": "1:673118911922:android:6d0bb991a2f211d2f8b8ab",
        "android_client_info": {
          "package_name": "com.example.chat_app"
        }
      },
      "oauth_client": [],
      "api_key": [
        {
          "current_key": "AIzaSyCEtSWyFM5Jh1PDuCqBFEl8brIkzVx_dm0"
        }
      ],
      "services": {
        "appinvite_service": {
          "other_platform_oauth_client": []
        }
      }
    }
  ],
  "configuration_version": "1"
}